stock_market/__init__.py
stock_market/__version__.py
stock_market/common/__init__.py
stock_market/common/factory.py
stock_market/common/json_mixins/__init__.py
stock_market/common/json_mixins/empty_json_mixin.py
stock_market/common/json_mixins/single_attribute_json_mixin.py
stock_market/core/__init__.py
stock_market/core/ohlc.py
stock_market/core/ohlc_fetcher.py
stock_market/core/stock_market.py
stock_market/core/stock_updater.py
stock_market/core/ticker.py
stock_market/core/ticker_ohlc.py
stock_market/core/time_series.py
stock_market/core/signal/__init__.py
stock_market/core/signal/sentiment.py
stock_market/core/signal/signal.py
stock_market/core/signal/signal_detector.py
stock_market/core/signal/signal_sequence.py
stock_market/ext/__init__.py
stock_market/ext/fetcher/__init__.py
stock_market/ext/fetcher/proxy_ohlc_fetcher.py
stock_market/ext/fetcher/register.py
stock_market/ext/fetcher/yahoo_ohlc_fetcher.py
stock_market/ext/indicator/__init__.py
stock_market/ext/indicator/exponential_moving_average.py
stock_market/ext/indicator/identity.py
stock_market/ext/indicator/moving_average.py
stock_market/ext/indicator/register.py
stock_market/ext/signal/__init__.py
stock_market/ext/signal/bi_monthly_signal_detector.py
stock_market/ext/signal/crossover_signal_detector.py
stock_market/ext/signal/death_cross_signal_detector.py
stock_market/ext/signal/golden_cross_signal_detector.py
stock_market/ext/signal/graph_signal_detector.py
stock_market/ext/signal/monthly_signal_detector.py
stock_market/ext/signal/register.py
stock_market_lib-0.7.2.dist-info/LICENSE
stock_market_lib-0.7.2.dist-info/METADATA
stock_market_lib-0.7.2.dist-info/WHEEL
stock_market_lib-0.7.2.dist-info/top_level.txt
stock_market_lib-0.7.2.dist-info/RECORD
